Library/MakeyIS.py
Library/__init__.py
MakeyIS-0.8.dist-info/METADATA
MakeyIS-0.8.dist-info/WHEEL
MakeyIS-0.8.dist-info/top_level.txt
MakeyIS-0.8.dist-info/RECORD
