Metadata-Version: 2.1
Name: MakeyIS
Version: 0.8
Summary: Библиотека обеспечивает усовершенствованное управление параметрами PyTest и логирование, упрощая создание и отладку автоматизированных тестов за счет интуитивно понятных декораторов и продвинутых функций логирования. Она идеально подходит для повышения эффективности и наглядности процесса тестирования.
Author: Makeenkov Igor
Author-email: pro100igo228@gmail.com
Requires-Dist: pytest
Requires-Dist: allure-pytest
Requires-Dist: allure-python-commons
